promptgit/__init__.py
promptgit/prompt.py
promptgit/repo.py
promptgit-0.2.5.dist-info/LICENSE
promptgit-0.2.5.dist-info/METADATA
promptgit-0.2.5.dist-info/WHEEL
promptgit-0.2.5.dist-info/RECORD
